c_index/__init__.py
c_index/c_index.py
c_index/c_index_R_interface.py
c_index/c_index_R_interface_test.py
c_index/c_index_test.py
c_index-0.0.2.dist-info/LICENSE
c_index-0.0.2.dist-info/METADATA
c_index-0.0.2.dist-info/WHEEL
c_index-0.0.2.dist-info/top_level.txt
c_index-0.0.2.dist-info/RECORD
